{
    "name": "SCORPION",
    "type": "BEP20",
    "symbol": "$SCORP",
    "decimals": 9,
    "website": "https://www.thescorpioncoin.com/",
    "description": "Scorpion token is a fair launch, community driven, hyper-deflationary DeFi protocol. Scorpion token holders benefit from passive rewards through static reflection, auto liquidity and auto burn. Proprietary anti-whale mechanisms built into the contract stop the supply from being controlled by syndicates.",
    "explorer": "https://bscscan.com/token/0x84750e8EfacC62be5AFe7221Cf149A2520Cb1b60",
    "status": "active",
    "id": "0x84750e8EfacC62be5AFe7221Cf149A2520Cb1b60",
    "links": [
        {
            "name": "github",
            "url": "https://github.com/scorpion-token/SCORPION"
        },
        {
            "name": "twitter",
            "url": "https://twitter.com/scorpionbsc"
        },
        {
            "name": "telegram",
            "url": "https://t.me/thescorpiontoken"
        }
    ]
}