{
    "name": "RichQuack",
    "symbol": "QUACK",
    "type": "BEP20",
    "decimals": 9,
    "description": "RichQUACK is a stealth fair launched token that has passsed Security Audit by TechRate, LP Locked, RUG-Proof & 100% community-driven project. Deflationary token with built in 10% transaction fee: 5% Safe Auto-Farm Redistributed to Holders including BlackHole, 5% for Auto LP",
    "website": "https://www.RichQuack.com",
    "explorer": "https://bscscan.com/token/0xD74b782E05AA25c50e7330Af541d46E18f36661C",
    "status": "active",
    "id": "0xd74b782e05aa25c50e7330af541d46e18f36661c"
}