{
    "name": "MacaronSwap Token",
    "symbol": "MCRN",
    "type": "BEP20",
    "decimals": 18,
    "description": "The future of decentralized exchange & farming platform on BSC",
    "website": "https://macaronswap.finance/",
    "explorer": "https://bscscan.com/token/0xacb2d47827C9813AE26De80965845D80935afd0B",
    "status": "active",
    "id": "0xacb2d47827c9813ae26de80965845d80935afd0b",
    "links": [
        {
            "name": "twitter",
            "url": "https://twitter.com/macaronswap"
        },
        {
            "name": "telegram",
            "url": "https://t.me/macaronswap"
        },
        {
            "name": "medium",
            "url": "https://medium.com/macaronswap"
        }
    ]
}