{
    "name": "Wrapped Bitcoin (WBTC)",
    "type": "ERC20",
    "symbol": "WBTC",
    "decimals": 8,
    "website": "https://www.wbtc.network/",
    "description": "Wrapped Bitcoin delivers the power of Bitcoin with the flexibility ",
    "explorer": "https://etherscan.io/token/0x2260FAC5E5542a773Aa44fBCfeDf7C193bc2C599",
    "status": "active",
    "id": "0x2260FAC5E5542a773Aa44fBCfeDf7C193bc2C599",
    "links": [
        {
            "name": "twitter",
            "url": "https://twitter.com/@WrappedBTC"
        },
        {
            "name": "github",
            "url": "https://github.com/wrapped BTC"
        }
    ],
    "tags": [
        "stablecoin"
    ]
}