{
    "name": "REI",
    "website": "https://rei.network",
    "description": "Rapid Economical Innovative",
    "explorer": "https://scan.rei.network",
    "research": "",
    "symbol": "REI",
    "type": "coin",
    "decimals": 18,
    "status": "active",
    "links": [
        {
            "name": "github",
            "url": "https://github.com/rei-network"
        },
        {
            "name": "twitter",
            "url": "https://twitter.com/GXChainGlobal"
        },
        {
            "name": "reddit",
            "url": "https://reddit.com/r/GXS/"
        },
        {
            "name": "discord",
            "url": "https://discord.com/invite/zhwWkXYtJt"
        }
    ]
}
