{
    "name": "Umbrella Network",
    "symbol": "UMB",
    "type": "ERC20",
    "decimals": 18,
    "description": "Umbrella Network a Community owned, Decentralized Oracle built on Layer 2 for DeFi and Blockchain Applications powered by UMB cryptocurrency",
    "website": "https://www.umb.network",
    "explorer": "https://etherscan.io/token/0x6fC13EACE26590B80cCCAB1ba5d51890577D83B2",
    "status": "active",
    "id": "0x6fc13eace26590b80cccab1ba5d51890577d83b2",
    "links": [
        {
            "name": "github",
            "url": "https://github.com/umbrella-network/overture"
        },
        {
            "name": "whitepaper",
            "url": "https://www.umb.network/wp-content/uploads/2021/02/umb_litepaper_design_v3.1.pdf"
        }
    ]
}