{
    "name": "Deep Blue USD",
    "type": "ARBITRUM",
    "symbol": "DBUSD",
    "decimals": 6,
    "website": "https://www.deepblue.to/",
    "description": "DBUSD is a USD fiat fully backed 1:1 stablecoin created and issued by Deep Blue with a focus on store of value, remittance, money transfers and trading settlement.",
    "explorer": "https://arbiscan.io/token/0x26B95c59BE6464f8fd7da08e84eB8475B9B7592C",
    "status": "active",
    "id": "0x26B95c59BE6464f8fd7da08e84eB8475B9B7592C",
    "links": [
        {
            "name": "x",
            "url": "https://x.com/DeepBlue_to"
        },
        {
            "name": "whitepaper",
            "url": "https://deepblue.to/"
        },
        {
            "name": "telegram",
            "url": "https://t.me/deepblueto"
        }
    ],
    "tags": [
        "stablecoin"
    ]
}