{
    "name": "Wrapped Bitcoin",
    "symbol": "WBTC",
    "type": "BRC20",
    "decimals": 8,
    "description": "Wrapped Bitcoin (WBTC) is the first ERC20 token backed 1:1 with Bitcoin.",
    "website": "https://wbtc.network",
    "explorer": "https://unisat.io/brc20/0x3C1BCa5a656e69edCD0D4E36BEbb3FcDAcA60Cf1",
    "status": "active",
    "id": "0x3C1BCa5a656e69edCD0D4E36BEbb3FcDAcA60Cf1",
    "links": [
        {
            "name": "whitepaper",
            "url": "https://wbtc.network/assets/wrapped-tokens-whitepaper.pdf"
        },
        {
            "name": "coinmarketcap",
            "url": "https://coinmarketcap.com/currencies/wrapped-bitcoin/"
        },
        {
            "name": "coingecko",
            "url": "https://coingecko.com/en/coins/wrapped-bitcoin/"
        }
    ],
    "tags": [
        "defi",
        "wrapped"
    ]
}