{
  "name": "FestCoin",
  "symbol": "FSC",
  "type": "ERC20",
  "decimals": 18,
  "description": "FestCoin (FSC) is a BEP-20 token designed to revolutionize the event industry through digital ticketing, staking, and community governance.",
  "website": "https://festcoin.io",
  "explorer": "https://bscscan.com/token/0x2C5B8AaF29F260137Af078E2580a4f7366B0af37",
  "status": "active",
  "id": "0x2C5B8AaF29F260137Af078E2580a4f7366B0af37",
  "email": "contactfestcoin@gmail.com",
  "links": [
    {
      "name": "twitter",
      "url": "https://x.com/festcoin_io"
    },
    {
      "name": "instagram",
      "url": "https://www.instagram.com/festcoin.io"
    },
    {
      "name": "telegram",
      "url": "https://t.me/festcoinofficial"
    },
    {
      "name": "github",
      "url": ""
    }
  ]
}
