{
    "name": "SHIBA INU",
    "website": "https://shibainuswap.dog/",
    "description": "ShibaSwap has many innovative features that help users earn & win bigger. ShibaSwap will be a whole ecosystem.",
    "explorer": "https://bscscan.com/token/0x02c5cE497ca02602c68407BfaB624996437c09B7",
    "type": "BEP20",
    "symbol": "SHIB",
    "decimals": 18,
    "status": "active",
    "id": "0x02c5cE497ca02602c68407BfaB624996437c09B7",
    "tags":[
        "deflationary"
     ],
    "links": [
        {
            "name": "telegram",
            "url": "https://t.me/SHIBASWAP_channel"
        },
        {
            "name": "twitter",
            "url": "https://twitter.com/shibaswap_dog?s=21"
        }
    ]
} 