{
    "name": "Buttcoin",
    "type": "SPL",
    "symbol": "BUTTCOIN",
    "decimals": 6,
    "description": "The most revolutionary memecoin in the crypto space. Built by the community, for the community.",
    "website": "https://www.buttcoin.lol/",
    "explorer": "https://solscan.io/token/77KhqraBouiU91KRchLPY8DYbVtfsH4nSBgHCd4UAwBY",
    "id": "77KhqraBouiU91KRchLPY8DYbVtfsH4nSBgHCd4UAwBY",
    "status": "active",
    "links": [
        {
            "name": "twitter",
            "url": "https://x.com/buttcoinlol"
        },
        {
            "name": "coinmarketcap",
            "url": "https://coinmarketcap.com/dexscan/solana/CXPNcmaC4yPbS1HEypeov3mFRK3a5HevJEdcdUki4zrD/"
        },
        {
            "name": "coingecko",
            "url": "https://coingecko.com/en/coins/buttcoin"
        }
    ],
        "tags": [
            "memes"
            ]
            }
            