{
    "name": "KEY",
    "website": "https://selfkey.org",
    "description": "SelfKey is a self-sovereign identity platform, built on the Ethereum blockchain, which aims to enable individuals and companies to have full ownership of their digital identity.",
    "explorer": "https://etherscan.io/token/0x4cc19356f2d37338b9802aa8e8fc58b0373296e7",
    "research": "https://research.binance.com/en/projects/selfkey",
    "type": "ERC20",
    "symbol": "KEY",
    "decimals": 18,
    "status": "active",
    "id": "0x4CC19356f2D37338b9802aa8E8fc58B0373296E7"
}