{
  "name": "DELTEC",
  "website": "https://t.me/deltec", 
  "description": "DELTEC is a utility token designed for seamless transactions and smart contract interactions on the blockchain.",
  "explorer": "https://bscscan.com/token/0xd7c4EF520254C433D321Ef7D50841Caab35aaf61",
  "type": "BEP20",
  "symbol": "DEL",
  "decimals": 18,
  "status": "active",
  "id": "0xd7c4EF520254C433D321Ef7D50841Caab35aaf61",
  "links": [
    {
      "name": "twitter",
      "url": "https://twitter.com/deltec"
    },
    {
      "name": "telegram",
      "url": "https://t.me/deltec"
    }
  ]
}