{
    "name": "X10FOUNDDATION",
    "website": "https://www.x10.farm/event",
    "description": "X10FOUDATION GACHA COIN",
    "explorer": "https://bscscan.com/address/0x3e1083a54F73d68D0340ae7aa0502fEB8F42784B",
    "symbol": "BULL",
    "type": "coin",
    "decimals": 18,
    "status": "active",
    "tags": [
        "staking-native"
    ],  
    "links": [
        {
            "name": "twitter",
            "url": "https://twitter.com/x10foundation"
        },
        {
            "name": "whitepaper",
            "url": "https://x10project.gitbook.io/x10.farm/"
        }
    ]
}
