{
    "name": "Crypto.com Coin",
    "website": "https://crypto.com/en/chain",
    "source_code": "",
    "white_paper": "https://www.crypto.com/images/chain_whitepaper.pdf",
    "short_description": "Crypto.com Chain will be a privacy preserving payment network that focuses on enabling crypto spending in the real world, powering the future of mobile money.",
    "description": "",
    "explorers": [
        {
            "name": "Etherscan",
            "url": "https://etherscan.io/token/0xa0b73e1ff0b80914ab6fe0444e65848c4c34450b"
        }
    ],
    "socials": [
        {
            "name": "Twitter",
            "url": "",
            "handle": ""
        },
        {
            "name": "Reddit",
            "url": "",
            "handle": ""
        }
    ],
    "data_source": "crowd"
}