{
    "name": "TheSaiyajin",
    "website": "https://bitclout.com/u/TheSaiyajin",
    "description": "The Saiyan Token is intended for all Dragon Ball fans and is only there for fun. It was created for educational purposes and is now available to all fans.",
    "explorer": "https://bscscan.com/token/0xe5be9643366eda836f7557270235871cd78f68b9",
    "type": "BEP20",
    "symbol": "JIN",
    "decimals": 18,
    "status": "active",
    "id": "0xe5be9643366eda836f7557270235871cd78f68b9"
}
