{
    "name": "SatoshiFx",
    "type": "BEP20",
    "symbol": "STF",
    "decimals": 18,
    "website": "https://satoshifx.io/",
    "description": "The Satoshfix is one of the leading wealth management companies. We have a team of financial experts available to offer you a strategic wealth management plan. Our team strives to understand your financial objectives and investment agenda to suggest you the most lucrative investment products.",
    "explorer": "https://bscscan.com/token/0x3003b0bea04FB8501e2f3A4a416E24422e6Dc1FA",
    "status": "active",
    "id": "0x3003b0bea04FB8501e2f3A4a416E24422e6Dc1FA",
    "links": [
        {
            "name": "twitter",
            "url": "https://twitter.com/Satoshifx6"
        },
        {
            "name": "telegram",
            "url": "https://t.me/satoshifx"
        },
        {
            "name": "source_code",
            "url": "https://bscscan.com/address/0x3003b0bea04fb8501e2f3a4a416e24422e6dc1fa#code"
        }
    ],
    "tags": [
        "staking"
    ]
}