{
    "name": "Sprai",
    "type": "BEP20",
    "symbol": "Sprai",
    "decimals": 18,
    "website": "https://spraicoin.github.io/",
    "description": "SPRAI is a Brazilian token created on BNB Smart Chain (BEP-20), combining innovation, sustainability and community engagement. The project supports environmental initiatives, such as the campaign “Plante e Ganhe SPRAI”, rewarding users for planting trees and contributing to nature preservation.",
    "explorer": "https://bscscan.com/token/0x7C7e518D6d91498BbD850a834e36a96661ac9B1B",
    "status": "active",
    "id": "0x7C7e518D6d91498BbD850a834e36a96661ac9B1B",
    "links": [
        {
            "name": "facebook",
            "url": "https://facebook.com/spraitoken"
        },
        {
            "name": "whitepaper",
            "url": "https://spraicoin.github.io/whitepaper-en.pdf"
        },
        {
            "name": "github",
            "url": "https://github.com/spraicoin/spraicoin.github.io"
        },
        {
            "name": "coinmarketcap",
            "url": "https://coinmarketcap.com/currencies/sprai/"
        },
        {
            "name": "telegram",
            "url": "https://t.me/spraitoken"
        }
    ],
    "tags": [
        "defi"
    ]
}