{
    "name": "Shadow",
    "type": "SONIC",
    "symbol": "SHADOW",
    "decimals": 18,
    "website": "https://www.shadow.so/",
    "description": "A Sonic-native concentrated liquidity exchange.The ultimate trading hub on Sonic.",
    "explorer": "https://sonicscan.org/token/0x3333b97138d4b086720b5ae8a7844b1345a33333",
    "status": "active",
    "id": "0x3333b97138D4b086720b5aE8A7844b1345a33333",
    "links": [
        {
            "name": "x",
            "url": "https://x.com/ShadowOnSonic"
        }
    ]
}