{
    "name": "LIMBO",
    "symbol": "LIMBO",
    "decimals": 6,
    "type": "SPL",
    "website": "https://pump.fun/coin/5UAMZkfNmuVcKzr2wo8Jqw4R1k8vfdAVJNN6h3bVpump",
    "description": "LIMBO tokens can be traded on decentralized exchanges and centralized crypto exchanges",
    "explorer": "https://solscan.io/token/5UAMZkfNmuVcKzr2wo8Jqw4R1k8vfdAVJNN6h3bVpump",
    "status": "active",
    "id": "5UAMZkfNmuVcKzr2wo8Jqw4R1k8vfdAVJNN6h3bVpump",
    "links": [
        {
            "name": "x",
            "url": "https://x.com/Limbo_ai"
        },
        {
            "name": "coingecko",
            "url": "https://coingecko.com/en/coins/limbo"
        }
    ]
}