{
    "name": "DappRadar",
    "symbol": "RADAR",
    "type": "CRC20",
    "decimals": 18,
    "description": "DappRadar aims to be one of the leading global NFT & DeFi DAPP store.",
    "website": "https://dappradar.com/",
    "explorer": "https://crypto.org/explorer/account/0xa58e3AeAeA3292c3E260378e55E9684C59E7A27a",
    "status": "active",
    "id": "0xa58e3AeAeA3292c3E260378e55E9684C59E7A27a",
    "links": [
        {
            "name": "github",
            "url": "https://github.com/dappradar"
        },
        {
            "name": "twitter",
            "url": "https://twitter.com/dappradar"
        },
        {
            "name": "coinmarketcap",
            "url": "https://coinmarketcap.com/currencies/dappradar/"
        },
        {
            "name": "telegram",
            "url": "https://t.me/joinchat/GdhNjQ8PMhCZ_a0CZutmXg"
        }
    ],
    "tags": [
        "nft",
        "defi"
    ]
}