{
  "name": "Hotpot Funds",
  "website": "https://hotpot.fund",
  "source_code": "https://github.com/HotpotFunds",
  "white_paper": "https://hotpot.fund/static/White_Paper_en.pdf",
  "short_description": "The Hotpot Funds is a transparent fund project on the public blockchain, consisting of a set of smart contracts deployed on the Ethereum blockchain.",
  "description": "Through Hotpot Fund, crypto currency investors can easily obtain the profits of investing in the DeFi project.",
  "explorer": "https://etherscan.io/address/0x615D8e5e1344B36A95F6ecd8e6CDA020E84dc25b"
}
