{
    "name": "Farmageddon",
    "type": "BEP20",
    "symbol": "FG",
    "decimals": 9,
    "website": "https://farmageddon.farm",
    "description": "A yield farming project used to power a platform used to bring the lucrative yet complicated process of yield farming to the masses.",
    "explorer": "https://bscscan.com/token/0x4492cA0AFF6D603e18Aea5075B49A5ff76b9Ea06",
    "status": "active",
    "id": "0x4492cA0AFF6D603e18Aea5075B49A5ff76b9Ea06",
    "links": [
        {
            "name": "twitter",
            "url": "https://twitter.com/Farmaggedon_"
        },
        {
            "name": "telegram",
            "url": "https://t.me/FARMAGEDDON_TOKEN"
        },
        {
            "name": "whitepaper",
            "url": "https://farmageddon.gitbook.io/farmageddon/farmageddon-whitepaper"
        }
    ]
}