{
    "name": "KAXAA",
    "type": "POLYGON",
    "symbol": "KAX",
    "decimals": 18,
    "website": "https://kaxaa.com/",
    "description": "The Kaxaa Token is a utility token used to access proprietary real estate data on the Kaxaa Platform and for use as currency in real estate transactions. The value of the Kaxaa Token is stabilized and determined by the proprietary Kaxaa Index algorithm based on real world real estate market indicators. The Kaxaa Token may be used in real world real estate transactions as a stabilized \"currency\" in and out of the Kaxaa platform.",
    "explorer": "https://polygonscan.com/token/0x5A55B82cDB9e8a700d52BbdeF3eE428666e9104A",
    "status": "active",
    "id": "0x5A55B82cDB9e8a700d52BbdeF3eE428666e9104A",
    "links": [
        {
            "name": "twitter",
            "url": "https://twitter.com/kaxaatoken"
        },
        {
            "name": "facebook",
            "url": "https://facebook.com/kaxaatoken"
        },
        {
            "name": "whitepaper",
            "url": "https://kaxaa.com/assets/files/KAXAA_White-Paper-2022.pdf"
        },
        {
            "name": "github",
            "url": "https://github.com/"
        },
        {
            "name": "telegram",
            "url": "https://t.me/kaxaatoken"
        }
    ],
    "tags": [
        "stablecoin"
    ]
}