{
    "name": "Donald Rich (DONAR)",
    "type": "ERC20",
    "symbol": "DONAR",
    "decimals": 18,
    "website": "https://sites.google.com/view/donaldrich/trang-ch%E1%BB%A7",
    "description": "",
    "explorer": "https://etherscan.io/token/0xBf2f8bA6408E13f12d14fa2d7dDe956fdca4aB32",
    "status": "active",
    "id": "0xBf2f8bA6408E13f12d14fa2d7dDe956fdca4aB32",
    "links": [
        {
            "name": "twitter",
            "url": "https://twitter.com/DONAR_rich"
        }
    ],
    "tags": [
        "memes"
    ]
}