
{ 
    "name": "Safe Energy",
    "type": "BEP20",
    "symbol": "EnergyX",
    "decimals": "8",
    "website": "https://safeenergyofficial.com/",
    "description": "SAFEENERGY,  $ENERGYX is a community driven deflationary charity token with future projects to reduce our carbon footprint by making renewable energy sources more accesible. $ENERGYX is on Binance Smart Chain (BSC) with a max supply of 1 Quadrillion.",
    "explorer": "https://bscscan.com/token/0xbbe899c61198d1826a43e20ea19efc46e50c2b00",
    "status": "active",
    "id": "0xbbe899c61198d1826a43e20ea19efc46e50c2b00"
}