{
    "name": "Coreto",
    "website": "https://coreto.io",
    "light_paper": "https://coreto.io/Coreto_Lightpaper_1.2-B.pdf",
    "description": "A reputation based, tokenized social platform orientated towards the crypto communities needs, educating retail investors about blockchain based projects.",
    "explorer": "https://etherscan.io/token/0x9c2dc0c3cc2badde84b0025cf4df1c5af288d835",
    "type": "ERC20",
    "symbol": "COR",
    "decimals": 18,
    "status": "active",
    "id": "0x9C2dc0c3CC2BADdE84B0025Cf4df1c5aF288D835",
    "links": [
        {
            "name": "github",
            "url": "https://github.com/coreto-io"
        },
        {
            "name": "twitter",
            "url": "https://twitter.com/Coretoio"
        },
        {
            "name": "telegram",
            "url": "https://t.me/Coreto"
        },
        {
            "name": "medium",
            "url": "https://medium.com/coreto"
        }
    ]
}