{
    "name": "Razor Network",
    "website": "https://razor.network/",
    "source_code": "https://github.com/razor-network",
    "white_paper": "https://razor.network/whitepaper.pdf",
    "description": "Razor Network is a decentralized oracle network, which connects smart contracts with real-world off-chain data in a fast, robust and secure way. The core of Razor Network is a set of smart contracts that can run on any Ethereum compatible blockchain. Razor Network is blockchain agnostic and will be integrated with multiple blockchains.",
    "explorer": "https://etherscan.io/address/0x50DE6856358Cc35f3A9a57eAAA34BD4cB707d2cd",
    "type": "ERC20",
    "symbol": "RAZOR",
    "decimals": 18,
    "status": "active",
    "id": "0x50DE6856358Cc35f3A9a57eAAA34BD4cB707d2cd",
    "socials": [
        {
            "name": "Twitter",
            "url": "https://twitter.com/razor_network",
            "handle": "razor_network"
        },
        {
            "name": "Medium",
            "url": "https://medium.com/razor-network",
            "handle": "razor-network"
        },
        {
            "name": "Telegram",
            "url": "https://t.me/razornetwork",
            "handle": "razornetwork"
        },
        {
            "name": "Discord",
            "url": "https://discord.gg/yvrHg85ycE",
            "handle": "RazorNetwork"
        },
        {
            "name": "Reddit",
            "url": "https://www.reddit.com/r/RazorNetwork",
            "handle": "RazorNetwork"
        }
    ]
}