{
    "name": "Oscar",
    "type": "ERC20",
    "symbol": "OSCAR",
    "decimals": 9,
    "website": "https://www.oscarshibatoken.com/",
    "description": "Oscar is a famous meme featuring a Shiba on a trampoline that went viral on the internet.",
    "explorer": "https://etherscan.io/token/0xebb66a88cedd12bfe3a289df6dfee377f2963f12",
    "status": "active",
    "id": "0xeBb66a88cEdd12bfE3a289df6DFEe377F2963F12",
    "links": [
        {
            "name": "x",
            "url": "https://x.com/oscar_shibainu"
        },
        {
            "name": "telegram",
            "url": "https://t.me/oscarshib"
        }
    ]
}