{
    "name": "Staked DePHY",
    "symbol": "stPHY",
    "type": "SPL",
    "decimals": 6,
    "description": "DePHY creates a decentralized service mesh infra that connects services, AIs and hardware.",
    "website": "https://dephy.io/",
    "explorer": "https://solscan.io/token/STPHyUo3XatFmsFEUFWiF8LtgZrHCgR2RFcRJiTtXyY",
    "status": "active",
    "id": "STPHyUo3XatFmsFEUFWiF8LtgZrHCgR2RFcRJiTtXyY",
    "links": [
        {
            "name": "x",
            "url": "https://x.com/dephynetwork"
        },
        {
            "name": "github",
            "url": "https://github.com/dephy-io"
        },
        {
            "name": "telegram",
            "url": "https://t.me/DePHYGroup"
        },
        {
            "name": "whitepaper",
            "url": "https://docs.dephy.io/other-resources/papers"
        }
    ],
    "tags": [
        "staking"
    ]
}

