{
    "name": "AND IT'S GONE",
    "symbol": "GONE",
    "type": "SPL",
    "decimals": 6,
    "description": "$GONE - Making Your Crypto Money Safe. The Popular Meme Now On Solana.",
    "website": "https://anditsgone.vip/",
    "explorer": "https://solscan.io/token/89D8aUdgHfyCRXYMxgo7ogHDbNnuVpHYRnqFfNF7gone",
    "status": "active",
    "id": "89D8aUdgHfyCRXYMxgo7ogHDbNnuVpHYRnqFfNF7gone",
    "links": [
        {
            "name": "x",
            "url": "https://x.com/AndItsGoneSOL"
        },
        {
            "name": "coinmarketcap",
            "url": "https://coinmarketcap.com/currencies/and-its-gone/"
        }
    ],
    "tags": [
        "memes"
    ]
}