{
    "name": "NEST Protocol",
    "website": "https://nestprotocol.org/",
    "description": "A defi infrastructure enabling all kinds of decentralized financial products trading",
    "explorer": "https://bscscan.com/token/0x98f8669f6481ebb341b522fcd3663f79a3d1a6a7",
    "symbol": "NEST",
    "type": "BEP20",
    "decimals": 18,
    "id": "0x98f8669F6481EbB341B522fCD3663f79A3d1A6A7",
    "status": "active",
    "tags": [
        "defi",
        "synthetics",
        "deflationary"
    ],
    "links": [
        {
            "name": "coinmarketcap",
            "url": "https://coinmarketcap.com/currencies/nest-protocol/"
        },
        {
            "name": "github",
            "url": "https://github.com/NEST-Protocol"
        },
        {
            "name": "twitter",
            "url": "https://twitter.com/NEST_Protocol"
        },
        {
            "name": "whitepaper",
            "url": "https://www.nestprotocol.org/doc/ennestwhitepaper.pdf"
        }
    ]
}