{
    "name": "Fluffington",
    "type": "SPL",
    "symbol": "Fluffi",
    "decimals": 6,
    "description": "• The Meme Connection: Fluffington, or SFLUFFl, has been dubbed by some on X as the 'first Grok-generated meme.' This isn't about a literal generation from Grok's Al (that would be too straightforward for the internet), but rather, it's a meme that's been recognized and perhaps inspired by the ethos of Grok, which, remember, is all about humor, wit, and a rebellious streak against the overly serious Al world.",
    "website": "https://fluffisol.io/",
    "explorer": "https://solscan.io/token/6CEjCg7Jo5RV9kFSgKx66rpW19nrsCmccD2bxfwpump",
    "id": "6CEjCg7Jo5RV9kFSgKx66rpW19nrsCmccD2bxfwpump",
    "status": "active",
    "links": [
        {
            "name": "twitter",
            "url": "https://twitter.com/fluffisol"
        },
        {
            "name": "coinmarketcap",
            "url": "https://coinmarketcap.com/currencies/fluffington/"
        },
        {
            "name": "coingecko",
            "url": "https://coingecko.com/en/coins/fluffington"
        }
    ],
        "tags": [
            "memes"
            ]
            }
            