{
    "name": "Dai Stablecoin",
    "symbol": "DAI.e",
    "type": "AVALANCHE",
    "decimals": 18,
    "description": "Multi-Collateral Dai, brings a lot of new and exciting features, such as support for new CDP collateral types and Dai Savings Rate.",
    "website": "https://makerdao.com/",
    "explorer": "https://snowtrace.io/token/0xd586E7F844cEa2F87f50152665BCbc2C279D8d70",
    "status": "active",
    "id": "0xd586E7F844cEa2F87f50152665BCbc2C279D8d70",
    "links": [
        {
            "name": "twitter",
            "url": "https://twitter.com/MakerDAO"
        },
        {
            "name": "whitepaper",
            "url": "https://makerdao.com/whitepaper/"
        },
        {
            "name": "coinmarketcap",
            "url": "https://coinmarketcap.com/currencies/multi-collateral-dai/"
        },
        {
            "name": "coingecko",
            "url": "https://coingecko.com/en/coins/dai/"
        }
    ],
    "tags": [
        "stablecoin"
    ]
}