{
    "name": "Ethena",
    "type": "ROBINHOODCHAIN",
    "symbol": "ENA",
    "decimals": 18,
    "description": "ENA is the governance token of Ethena, the protocol behind the USDe synthetic dollar.",
    "website": "https://ethena.fi",
    "explorer": "https://8crv4vmq6tiu1yqr.blockscout.com/token/0x58538e6A46E07434d7E7375Bc268D3cb839C0133",
    "status": "active",
    "id": "0x58538e6A46E07434d7E7375Bc268D3cb839C0133",
    "links": [
        {
            "name": "x",
            "url": "https://x.com/ethena_labs"
        }
    ],
    "tags": [
        "governance"
    ]
}
