{
    "name": "abrdn Physical Palladium Shares ETF (Ondo Tokenized)",
    "type": "SPL",
    "symbol": "PALLon",
    "decimals": 9,
    "description": "PALLon is the Ondo Tokenized version of the abrdn Physical Palladium Shares ETF, giving tokenholders economic exposure similar to holding PALL and reinvesting any dividends. Additional restrictions apply. Learn more at https://ondo.finance/gm.",
    "website": "https://ondo.finance/",
    "explorer": "https://solscan.io/token/P7hTXnKk2d2DyqWnefp5BSroE1qjjKpKxg9SxQqondo",
    "status": "active",
    "id": "P7hTXnKk2d2DyqWnefp5BSroE1qjjKpKxg9SxQqondo",
    "links": [
        {
            "name": "x",
            "url": "https://x.com/ondofinance"
        },
        {
            "name": "coingecko",
            "url": "https://coingecko.com/en/coins/abrdn-physical-palladium-shares-etf-ondo-tokenized-stocks"
        },
        {
            "name": "coinmarketcap",
            "url": "https://coinmarketcap.com/currencies/abrdn-physical-palladium-shares-tokenized-etf-ondo/"
        }
    ],
    "tags": [
        "RWA"
    ]
}