{
  "name": "Grass",
  "symbol": "Grass",
  "type": "SPL",
  "decimals": 9,
  "description": "Grass is building the first open internet scale web crawl. Today, the network is powered by over 3 million users who are running nodes to scrape petabytes of data for AI models.",
  "website": "https://www.getgrass.io/",
  "explorer": "https://solscan.io/token/Grass7B4RdKfBCjTKgSqnXkqjwiGvQyFbuSCUJr3XXjs",
  "status": "active",
  "id": "Grass7B4RdKfBCjTKgSqnXkqjwiGvQyFbuSCUJr3XXjs",
  "links": [
    {
      "name": "x",
      "url": "https://x.com/getgrass_io"
    },
    {
      "name": "coinmarketcap",
      "url": "https://coinmarketcap.com/currencies/grass/"
    }
  ]
}