{
    "name": "Dogechain",
    "type": "coin",
    "symbol": "DC",
    "decimals": 18,
    "website": "https://dogechain.dog/",
    "description": "Dogechain supercharges $Dogecoin to bring crypto applications like NFTs, games, and DeFi to the $Dogecoin community. Unfortunately, $Dogecoin cannot support any of these applications.",
    "explorer": "https://explorer.dogechain.dog",
    "status": "active",
    "links": [
        {
            "name": "twitter",
            "url": "https://twitter.com/dogechainfamily"
        },
        {
            "name": "telegram",
            "url": "https://t.me/DogeChainOfficial"
        },
        {
            "name": "coinmarketcap",
            "url": "https://coinmarketcap.com/ru/currencies/dogechain/"
        }
    ],
    "tags": [
        "defi",
        "nft"
    ]
}
