{
    "name": "Mining USF Finance - Together We Grow",
    "website": "https://jbf.finance",
    "short_description": "Mining USF Finance - Together We Grow",
    "explorer": "https://etherscan.io/token/0x31733F69232Bdb189934B54A18Ab9bDe5144E74d",
    "socials": [
        {
            "name": "Facebook",
            "url": "https://www.facebook.com/USFinance-104383688132784",
            "handle": "USFinance"
        },
        {
            "name": "Youtube",
            "url": "https://www.youtube.com/channel/UCENEnXHd1ATarqrhjhseG0g",
            "handle": "USFinance"
        },
        {
            "name": "Instagram",
            "url": "https://www.instagram.com/usfinance.media",
            "handle": "USFinance"
        },
        {
            "name": "Tiktok",
            "url": "https://vt.tiktok.com/ZSQNQttr",
            "handle": "USFinance"
        }
    ]
}