{
    "name": "Nya",
    "type": "OPTIMISM",
    "symbol": "NYA",
    "decimals": 18,
    "website": "https://www.nya.vip",
    "description": "Explore the cultural phenomenon of Nya - the playful cat sound that's become a symbol of joy and connection. Discover how this simple word unites fans worldwide.",
    "explorer": "https://optimistic.etherscan.io/token/0x38F9bf9dCe51833Ec7f03C9dC218197999999999",
    "status": "active",
    "id": "0x38F9bf9dCe51833Ec7f03C9dC218197999999999",
    "links": [
        {
            "name": "twitter",
            "url": "https://twitter.com/NyaOnEarth"
        },
        {
            "name": "telegram",
            "url": "https://t.me/NyaOnEarth"
        },
        {
            "name": "discord",
            "url": "https://discord.com/invite/3V8gZFP5kb"
        },
        {
            "name": "docs",
            "url": "https://wiki.nya.vip"
        }
    ],
    "tags": [
        "memes",
        "nft"
    ]
}