{
    "name": "Let's Go Brandon Coin",
    "type": "POLYGON",
    "symbol": "LGBC",
    "decimals": 18,
    "website": "https://letsgobrandoncoin.org",
    "description": "Coin that embodies the chant from the crowds for freedom of speech, fun and sportsmanship.\nThere is a time lock of 24 hours for the investor to be able to release the tokens to its wallet.\nEvery day there is a 1% reduction on the amount of tokens received per USDC invested. This way USDCs can be invested in profitable operations and with the profits, the executive team will be able to conduct the monetary policy. ",
    "explorer": "https://polygonscan.com/token/0x843844Bc6642650D65901d32111fac6773998904",
    "status": "active",
    "id": "0x843844Bc6642650D65901d32111fac6773998904",
    "links": [
        {
            "name": "twitter",
            "url": "https://twitter.com/LGBCoin"
        },
        {
            "name": "github",
            "url": "https://github.com/lgbcoin"
        },
        {
            "name": "reddit",
            "url": "https://reddit.com/r/LGBCoin"
        },
        {
            "name": "youtube",
            "url": "https://youtube.com/channel/UCwe3udqd4sGoFcCWPGfRkiw"
        },
        {
            "name": "medium",
            "url": "https://letsgobrandoncoin.medium.com/"
        },
        {
            "name": "discord",
            "url": "https://discord.com/invite/FDG4FMcM"
        }
    ]
}