{
    "name": "FLOKI CEO",
    "type": "BEP20",
    "symbol": "FLOKICEO",
    "decimals": 9,
    "website": "https://flokiceo.io",
    "description": "FLOKICEO a Meme token in the BSC ecosystem, $FlokiCeo is comunity-driven cannot control by anyone. Instant Usage Rewards for every active user transaction a 7% $FLOKICEO reward is granted to holders (decentralized wallets only)",
    "explorer": "https://bscscan.com/token/0x45289007706E7Ee7B42b1fA506661d97740Edfb4",
    "status": "active",
    "id": "0x45289007706E7Ee7B42b1fA506661d97740Edfb4",
    "links": [
        {
            "name": "twitter",
            "url": "https://twitter.com/FlokiCeoo"
        },
        {
            "name": "github",
            "url": "https://github.com/flokiceo/"
        },
        {
            "name": "telegram",
            "url": "https://t.me/flokiceogroup"
        },
        {
            "name": "telegram_news",
            "url": "https://t.me/"
        },
        {
            "name": "whitepaper",
            "url": "https://flokiceo.io/Flokiceowp.pdf"
        },
        {
            "name": "coinmarketcap",
            "url": "https://coinmarketcap.com/currencies/floki-ceo"
        },
        {
            "name": "coingecko",
            "url": "https://coingecko.com/en/coins/floki-ceo"
        }
    ],
    "tags": [
        "memes"
    ]
}