{
    "name": "Tardigrades.Finance",
    "symbol": "TRDG",
    "type": "ERC20",
    "decimals": 9,
    "description": "Tardigrades Finance offers frictionless rewards 5% Tax with 2.5% Burn / and 2.5% back to Holders for each transaction.",
    "website": "https://www.tardigrades.finance/",
    "explorer": "https://etherscan.io/token/0x92a42db88ed0f02c71d439e55962ca7cab0168b5",
    "status": "active",
    "id": "0x92a42db88ed0f02c71d439e55962ca7cab0168b5",
    "tags": [
        "deflationary"
    ]
}