{
    "name": "Catboy",
    "type": "ERC20",
    "symbol": "CATBOY",
    "decimals": 18,
    "website": "https://www.catboy.io/",
    "description": "Catboy is an NFT project with a fusion of meme & anime, while 'catified.' With reward utilities & innovative and Interactive NFTs with AI integration.",
    "explorer": "https://etherscan.io/token/0x0DceE5F694E492F0DD842a7FBE5BEd4C6E4665a6",
    "status": "active",
    "id": "0x0DceE5F694E492F0DD842a7FBE5BEd4C6E4665a6",
    "links": [
        {
            "name": "twitter",
            "url": "https://twitter.com/catboy_io"
        },
        {
            "name": "coinmarketcap",
            "url": "https://coinmarketcap.com/currencies/cat-boy/"
        }
    ]
} 