{
    "name": "Superalgos",
    "website": "https://superalgos.org/",
    "description": "Superalgos is pioneering the Decentralized Trading space building the first Open Trading Intelligence Network. The Superalgos (SA) token incentivizes contributions of code, trading intelligence, and project development. You may use it to gain priority access to trading signals in the Superalgos Network and to participate in project governance.",
    "explorer": "https://bscscan.com/token/0xfb981ed9a92377ca4d75d924b9ca06df163924fE",
    "type": "BEP20",
    "symbol": "SA",
    "decimals": 18,
    "status": "active",
    "id": "0xfb981ed9a92377ca4d75d924b9ca06df163924fd",
    "links": [
        {
            "name": "telegram",
            "url": "https://t.me/superalgoscommunity"
        },
        {
            "name": "discord",
            "url": "https://discord.com/invite/CGeKC6WQQb"
        },
        {
            "name": "twitter",
            "url": "https://twitter.com/superalgos"
        },
        {
            "name": "medium",
            "url": "https://medium.com/superalgos"
        },
        {
            "name": "youtube",
            "url": "https://www.youtube.com/c/superalgos"
        },
        {
            "name": "facebook",
            "url": "https://www.facebook.com/superalgos"
        },
        {
            "name": "reddit",
            "url": "https://www.reddit.com/r/Superalgos/"
        },
        {
            "name": "nomics",
            "url": "https://nomics.com/assets/sa-superalgos"
        }
    ]
}