{
    "name": "just buy $1 worth of this coin",
    "type": "SPL",
    "symbol": "$1",
    "decimals": 6,
    "description": "$1 is a wholly community-owned movement and meme coin. After the dev dumped the coin, the $1 community organized and took over control of the coin to realize the movement’s original purpose - to send $1 to $1 and beyond.",
    "website": "https://1dollarsol.com/",
    "explorer": "https://solscan.io/token/GHichsGq8aPnqJyz6Jp1ASTK4PNLpB5KrD6XrfDjpump",
    "id": "GHichsGq8aPnqJyz6Jp1ASTK4PNLpB5KrD6XrfDjpump",
    "status": "active",
    "links": [
        {
            "name": "x",
            "url": "https://x.com/1DollarSol"
        },
        {
            "name": "coinmarketcap",
            "url": "https://coinmarketcap.com/currencies/just-buy-1-worth-of-this-coin/"
        },
        {
            "name": "coingecko",
            "url": "https://coingecko.com/en/coins/just-buy-1-worth-of-this-coin"
        }
    ],
    "tags": [
        "memes"
    ]
}
    