{
    "name": "Jade Currency",
    "type": "BEP20",
    "symbol": "JADE",
    "decimals": 18,
    "website": "https://www.jadecurrency.com",
    "description": "Jade is committed to changing the world by creating the first ever NFT marketplace and metaverse shop for precious gems such as jade where buyers can purchase in cryptocurrency",
    "explorer": "https://etherscan.io/token/0x330f4fe5ef44b4d0742fe8bed8ca5e29359870df",
    "status": "active",
    "id": "0x330F4fe5ef44B4d0742fE8BED8ca5E29359870DF"
}